flask_files/__init__.py
flask_files/file.py
flask_files/form.py
flask_files/images.py
flask_files-0.2.0.dist-info/WHEEL
flask_files-0.2.0.dist-info/METADATA
flask_files-0.2.0.dist-info/RECORD
