Metadata-Version: 2.4
Name: flask-files
Version: 0.2.0
Summary: Uploaded files management based on fsspec
Author: Maxime Bouroumeau-Fuseau
Author-email: Maxime Bouroumeau-Fuseau <maxime.bouroumeau@gmail.com>
License-Expression: MIT
Requires-Dist: flask>=3.0.0,<4.0.0
Requires-Dist: fsspec>=2023.12.2
Requires-Python: >=3.10
Project-URL: Repository, https://github.com/hyperflask/flask-files
